stand_da/__init__.py
stand_da/ad_da.py
stand_da/conditioning.py
stand_da/gen_data.py
stand_da/kernels.py
stand_da/layers.py
stand_da/operations.py
stand_da/si_stand_da.py
stand_da/util.py
stand_da-0.1.2.dist-info/licenses/LICENSE
stand_da-0.1.2.dist-info/METADATA
stand_da-0.1.2.dist-info/WHEEL
stand_da-0.1.2.dist-info/top_level.txt
stand_da-0.1.2.dist-info/RECORD
