Metadata-Version: 2.4
Name: stand_da
Version: 0.1.2
License-File: LICENSE
Requires-Dist: mpmath==1.3.0
Requires-Dist: numpy==2.1.0
Requires-Dist: scipy==1.15.3
Requires-Dist: torch
Requires-Dist: numba
Dynamic: description
Dynamic: description-content-type
Dynamic: license-file
Dynamic: requires-dist
